.bumpversion.cfg
.gitignore
.travis.yml
LICENSE.txt
MANIFEST.in
Makefile
README.rst
README_continuous_integration.md
pypackage.mk
requirements.txt
setup.py
shippable.yml
.circleci/config.yml
demos/custom_classes.py
demos/custom_conds_in_docstrings.py
docs/.gitignore
docs/Makefile
docs/docs.mk
docs/epydoc.cfg
docs/gitadd.zsh
docs/sphinxtogithub.py
docs/source/api.rst
docs/source/api_lowlevel.rst
docs/source/api_reference.rst
docs/source/changelog.rst
docs/source/conf.py
docs/source/contractsmeta.rst
docs/source/credits.rst
docs/source/definitions.txt
docs/source/download.html
docs/source/fork.html
docs/source/index.rst
docs/source/menu.txt
docs/source/new_contract.rst
docs/source/old_index.txt
docs/source/overhead.rst
docs/source/reference.rst
docs/source/tour.rst
docs/source/tracking.html
docs/source/api/contracts.library.rst
docs/source/api/contracts.rst
docs/source/api/contracts.testing.library.rst
docs/source/api/contracts.testing.rst
docs/source/api/contracts.useful_contracts.rst
docs/source/api/modules.rst
docs/source/my_static/.empty
docs/source/my_templates/layout.html
docs/source/use_cases/class_contracts.py
docs/source/use_cases/meta.py
docs/source/use_cases/predicate.py
docs/source/use_cases/user_defined.py
src/PyContracts.egg-info/PKG-INFO
src/PyContracts.egg-info/SOURCES.txt
src/PyContracts.egg-info/dependency_links.txt
src/PyContracts.egg-info/requires.txt
src/PyContracts.egg-info/top_level.txt
src/contracts/__init__.py
src/contracts/backported.py
src/contracts/docstring_parsing.py
src/contracts/enabling.py
src/contracts/inspection.py
src/contracts/interface.py
src/contracts/main.py
src/contracts/main_actual.py
src/contracts/metaclass.py
src/contracts/pyparsing_utils.py
src/contracts/syntax.py
src/contracts/test_registrar.py
src/contracts/utils.py
src/contracts-py3k-test/test_py3k_annotations.py
src/contracts/library/__init__.py
src/contracts/library/arithmetic.py
src/contracts/library/array.py
src/contracts/library/array_ops.py
src/contracts/library/attributes.py
src/contracts/library/comparison.py
src/contracts/library/compositions.py
src/contracts/library/dicts.py
src/contracts/library/dummy.py
src/contracts/library/extensions.py
