Metadata-Version: 1.1
Name: PyContracts
Version: 1.8.6
Summary: PyContracts is a Python package that allows to declare constraints on function parameters and return values. Contracts can be specified using Python3 annotations, in a decorator, or inside a docstring :type: and :rtype: tags. PyContracts supports a basic type system, variables binding, arithmetic constraints, and has several specialized contracts (notably for Numpy arrays), as well as an extension API.
Home-page: http://andreacensi.github.com/contracts/
Author: Andrea Censi
Author-email: censi@mit.edu
License: LGPL
Download-URL: http://github.com/AndreaCensi/contracts/tarball/1.8.6
Keywords: type checking,value checking,contracts
Platform: UNKNOWN
Classifier: Development Status :: 5 - Production/Stable
Classifier: Intended Audience :: Developers
Classifier: License :: OSI Approved :: GNU Library or Lesser General Public License (LGPL)
Classifier: Topic :: Software Development :: Quality Assurance
Classifier: Topic :: Software Development :: Documentation
Classifier: Topic :: Software Development :: Testing
